{"type":"FeatureCollection","features":[{"type":"Feature","properties":{"marker-color":"#7e7e7e","marker-size":"medium","marker-symbol":"","name":"École des garçons","start":1817,"end":"unknown"},"geometry":{"type":"Point","coordinates":[-17.3986154794693,14.667375216672392]}}]}